LICENSE
MANIFEST.in
README.rst
editor.png
fullscreen.png
setup.py
django_epiceditor.egg-info/PKG-INFO
django_epiceditor.egg-info/SOURCES.txt
django_epiceditor.egg-info/dependency_links.txt
django_epiceditor.egg-info/requires.txt
django_epiceditor.egg-info/top_level.txt
epiceditor/__init__.py
epiceditor/forms.py
epiceditor/models.py
epiceditor/widgets.py
epiceditor/static/epiceditor/Jakefile.js
epiceditor/static/epiceditor/docs/css/main.css
epiceditor/static/epiceditor/docs/css/prettify.css
epiceditor/static/epiceditor/docs/images/bg-glow.png
epiceditor/static/epiceditor/docs/images/epiceditor-logo.png
epiceditor/static/epiceditor/docs/images/zip.png
epiceditor/static/epiceditor/docs/js/jquery.min.js
epiceditor/static/epiceditor/docs/js/main.js
epiceditor/static/epiceditor/docs/js/prettify.js
epiceditor/static/epiceditor/images/edit.png
epiceditor/static/epiceditor/images/fullscreen.png
epiceditor/static/epiceditor/images/preview.png
epiceditor/static/epiceditor/js/epiceditor.js
epiceditor/static/epiceditor/js/epiceditor.min.js
epiceditor/static/epiceditor/src/editor.js
epiceditor/static/epiceditor/test/helpers.js
epiceditor/static/epiceditor/test/server.js
epiceditor/static/epiceditor/test/test.edit.js
epiceditor/static/epiceditor/test/test.emit.js
epiceditor/static/epiceditor/test/test.enterFullscreen.js
epiceditor/static/epiceditor/test/test.exitFullscreen.js
epiceditor/static/epiceditor/test/test.exportFile.js
epiceditor/static/epiceditor/test/test.getElement.js
epiceditor/static/epiceditor/test/test.getFiles.js
epiceditor/static/epiceditor/test/test.importFile.js
epiceditor/static/epiceditor/test/test.is.js
epiceditor/static/epiceditor/test/test.load.js
epiceditor/static/epiceditor/test/test.on.js
epiceditor/static/epiceditor/test/test.open.js
epiceditor/static/epiceditor/test/test.options.js
epiceditor/static/epiceditor/test/test.preview.js
epiceditor/static/epiceditor/test/test.reflow.js
epiceditor/static/epiceditor/test/test.remove.js
epiceditor/static/epiceditor/test/test.removeListener.js
epiceditor/static/epiceditor/test/test.rename.js
epiceditor/static/epiceditor/test/test.save.js
epiceditor/static/epiceditor/test/test.unload.js
