Metadata-Version: 1.1
Name: django-epiceditor
Version: 0.2.3
Summary: A django app that allows the easy addition of EpicEditor markdown editor to a django form field, whether in a custom app or the Django Admin.
Home-page: https://github.com/barraq/django-epiceditor
Author: Remi Barraquand
Author-email: dev@remibarraquand.com
License: LICENSE
Platform: UNKNOWN
Classifier: Development Status :: 5 - Production/Stable
Classifier: Environment :: Web Environment
Classifier: Framework :: Django
Classifier: Intended Audience :: Developers
Classifier: License :: OSI Approved :: BSD License
Classifier: Operating System :: OS Independent
Classifier: Programming Language :: Python
